setup.py
Mnml_Pygments_Lexer.egg-info/PKG-INFO
Mnml_Pygments_Lexer.egg-info/SOURCES.txt
Mnml_Pygments_Lexer.egg-info/dependency_links.txt
Mnml_Pygments_Lexer.egg-info/entry_points.txt
Mnml_Pygments_Lexer.egg-info/top_level.txt
mnml_lexer/__init__.py