Metadata-Version: 1.0
Name: Mnml-Pygments-Lexer
Version: 1.0.1
Summary: Pygments Lexer for the Mnml language
Home-page: http://getmnml.com
Author: Emil Loer
Author-email: emil@koffietijd.net
License: BSD
Platform: UNKNOWN
